MANIFEST.in
README.md
public_readme.md
pyproject.toml
setup.py
cannerflow/__init__.py
cannerflow/client.py
cannerflow/dto.py
cannerflow/exceptions.py
cannerflow/logging.py
cannerflow/query.py
cannerflow/request.py
cannerflow/saved_query.py
cannerflow/utils.py
cannerflow/workspace.py
cannerflow/adapters/__init__.py
cannerflow/adapters/query_reader/__init__.py
cannerflow/adapters/query_reader/api_fetch_reader.py
cannerflow/adapters/query_reader/parquet_reader.py
cannerflow/file/__init__.py
cannerflow/file/csv_wrapper.py
cannerflow/file/file.py
cannerflow/file/image_wrapper.py
cannerflow/file/json_wrapper.py
cannerflow/payloads/__init__.py
cannerflow/payloads/create_sql_query.py
cannerflow/payloads/delete_file.py
cannerflow/payloads/delete_statement.py
cannerflow/payloads/operation_type.py
cannerflow/payloads/sql_query.py
cannerflow/payloads/sql_result_pagination.py
cannerflow_python_client.egg-info/PKG-INFO
cannerflow_python_client.egg-info/SOURCES.txt
cannerflow_python_client.egg-info/dependency_links.txt
cannerflow_python_client.egg-info/requires.txt
cannerflow_python_client.egg-info/top_level.txt
tests/__init__.py
tests/config.py
tests/conftest.py
tests/test_client.py
tests/test_csv_wrapper.py
tests/test_parquet.py
tests/test_query.py
tests/test_utils.py